cherrypy_dynpool.py
cherrypy_dynpool-2.4.0.dist-info/LICENSE
cherrypy_dynpool-2.4.0.dist-info/METADATA
cherrypy_dynpool-2.4.0.dist-info/WHEEL
cherrypy_dynpool-2.4.0.dist-info/top_level.txt
cherrypy_dynpool-2.4.0.dist-info/RECORD
