Metadata-Version: 2.1
Name: cherrypy-dynpool
Version: 2.4.0
Summary: A dynamic thread pool tool for CherryPy.
Home-page: https://github.com/tabo/cherrypy-dynpool/
Author: Gustavo Picon
Author-email: tabo@tabo.pe
License: UNKNOWN
Platform: UNKNOWN
Classifier: Development Status :: 5 - Production/Stable
Classifier: Intended Audience :: Developers
Classifier: License :: OSI Approved :: Apache Software License
Classifier: Programming Language :: Python
Classifier: Programming Language :: Python :: 2.6
Classifier: Programming Language :: Python :: 2.7
Classifier: Programming Language :: Python :: 3
Classifier: Programming Language :: Python :: 3.2
Classifier: Programming Language :: Python :: 3.3
Classifier: Programming Language :: Python :: 3.4
Classifier: Programming Language :: Python :: 3.5
Classifier: Operating System :: OS Independent
Classifier: Topic :: Software Development :: Libraries
Requires-Dist: CherryPy (>=3.2)
Requires-Dist: dynpool (<3.0,>=2.0)
Provides-Extra: testing
Requires-Dist: pytest ; extra == 'testing'
